rich_string_builder/string_builder.py
rich_string_builder-0.0.1.dist-info/LICENSE
rich_string_builder-0.0.1.dist-info/METADATA
rich_string_builder-0.0.1.dist-info/WHEEL
rich_string_builder-0.0.1.dist-info/top_level.txt
rich_string_builder-0.0.1.dist-info/RECORD
