Metadata-Version: 2.1
Name: rich-string-builder
Version: 0.0.1
Summary: Text preprocessor for building strings for the rich library
Author-email: BD Himes <benjamindhimes@gmail.com>
License: MIT License
Project-URL: homepage, https://github.com/thewhaleking/rich-string-builder
Project-URL: Repository, https://github.com/thewhaleking/rich-string-builder
Requires-Python: >=3.7
License-File: LICENSE
Provides-Extra: dev
Requires-Dist: rich; extra == "dev"
Requires-Dist: pytest; extra == "dev"
